ORTipy2/__init__.py
ORTipy2/gomory_ilpp.py
ORTipy2/graphical_lpp.py
ORTipy2/perturbation_method.py
ORTipy2/simplex_lpp.py
ORTipy2-0.3.dist-info/LICENSE
ORTipy2-0.3.dist-info/METADATA
ORTipy2-0.3.dist-info/WHEEL
ORTipy2-0.3.dist-info/top_level.txt
ORTipy2-0.3.dist-info/RECORD
